python_readiness.py
python_readiness-2.2.dist-info/entry_points.txt
python_readiness-2.2.dist-info/LICENSE
python_readiness-2.2.dist-info/WHEEL
python_readiness-2.2.dist-info/METADATA
python_readiness-2.2.dist-info/RECORD
