Metadata-Version: 2.1
Name: python_readiness
Version: 2.2
Summary: Are your dependencies ready for new Python?
Author: Shantanu Jain
Author-email: hauntsaninja@gmail.com
Requires-Python: >=3.9
Requires-Dist: aiohttp>=3.10
Requires-Dist: packaging>=24
Project-URL: homepage, https://github.com/hauntsaninja/python_readiness
Project-URL: repository, https://github.com/hauntsaninja/python_readiness
